{
    "meta_data": {
        "type": "Resonator Spectroscopy",
        "plot_properties": {
            "x_label": "Resonator Frequency [GHz]",
            "y_label": "Amplitude [a.u.]",
            "title": "Resonator Spectroscopy"
        },
        "experiment_properties": {
            "qubit": "q2",
            "repetitions": 1000
        },
        "qubit_parameters": {
            "q1": {
                "qb_freq": 4723300000,
                "drive_amp": 1,
                "drive_len": 4e-05,
                "pi_amp": 0.1277679833823185,
                "pi_len": 4e-08,
                "res_freq": 5250000000.0,
                "res_amp": 0.35,
                "res_len": 2e-06,
                "qb_amp_spec": 1.0,
                "qb_lo": 4600000000.0,
                "res_lo": 5600000000.0,
                "flux_bias": -0.0183,
                "anharmnonicity": 190300000,
                "w125": 4628150000.0,
                "ro_delay": 1e-07,
                "ro_int_delay": 4e-08,
                "angle": -2.7369100144220284,
                "ge": [
                    0.00011656060279059207,
                    0.00029401170412310417
                ]
            },
            "q2": {
                "qb_freq": 4323900000.0,
                "drive_amp": 0.5,
                "drive_len": 4e-05,
                "pi_amp": 0.1401419087323477,
                "pi_len": 4e-08,
                "res_freq": 4930000000.0,
                "res_amp": 0.75,
                "res_len": 2e-06,
                "qb_amp_spec": 1.0,
                "qb_lo": 4600000000.0,
                "res_lo": 5600000000.0,
                "flux_bias": -0.884,
                "anharmnonicity": 190300000,
                "w125": 4220000000.0,
                "ro_delay": 2e-08,
                "ro_int_delay": 4e-08,
                "angle": -6.222312663218462,
                "ge": [
                    3.6510377574210706e-06,
                    -2.3955848695694695e-05
                ]
            },
            "q3": {
                "qb_freq": 4533000000,
                "drive_amp": 0.5,
                "drive_len": 4e-05,
                "pi_amp": 0.12311032872520918,
                "pi_len": 4e-08,
                "res_freq": 6155000000.0,
                "res_amp": 0.4,
                "res_len": 2e-06,
                "qb_amp_spec": 1.0,
                "qb_lo": 4600000000.0,
                "res_lo": 5600000000.0,
                "flux_bias": -0.83678,
                "anharmnonicity": 208220000.0,
                "w125": 4428890000.0,
                "ro_delay": 2e-08,
                "ro_int_delay": 4e-08,
                "angle": -7.852623448891259,
                "ge": [
                    -0.0003101590383918415,
                    -0.00021195280752536226
                ]
            },
            "q4": {
                "qb_freq": 4323900000.0,
                "drive_amp": 0.2,
                "drive_len": 4e-05,
                "pi_amp": 0.10853792597888534,
                "pi_len": 4e-08,
                "res_freq": 5836500000.0,
                "res_amp": 0.4,
                "res_len": 3e-06,
                "qb_amp_spec": 1.0,
                "qb_lo": 4600000000.0,
                "res_lo": 5600000000.0,
                "flux_bias": -0.77725,
                "anharmnonicity": 208390000.0,
                "w125": 4326260000.0,
                "ro_delay": 2e-08,
                "ro_int_delay": 4e-08,
                "angle": -2.4443143991298353,
                "ge": [
                    -0.00042636181776059036,
                    -0.0002827908846892121
                ]
            },
            "q5": {
                "qb_freq": 4402900000.0,
                "drive_amp": 0.5,
                "drive_len": 4e-05,
                "pi_amp": 0.062420508762112345,
                "pi_len": 4e-08,
                "res_freq": 5546000000.0,
                "res_amp": 0.3,
                "res_len": 2e-06,
                "qb_amp_spec": 1.0,
                "qb_lo": 4600000000.0,
                "res_lo": 5600000000.0,
                "flux_bias": -1,
                "anharmnonicity": 208390000.0,
                "w125": 4326260000.0,
                "ro_delay": 2e-08,
                "ro_int_delay": 4e-08,
                "angle": -2.996056349613848,
                "ge": [
                    -0.00040741841066762414,
                    -0.00023190881940069458
                ]
            },
            "c13": {
                "flux_bias": -0.003
            },
            "c23": {
                "flux_bias": -0.1
            },
            "c43": {
                "flux_bias": -0.04,
                "CZ_flux": -0.145,
                "CZ_length": 8e-08
            },
            "c53": {
                "flux_bias": 0
            }
        }
    },
    "data": {
        "x": [
            4830000000.0,
            4832000000.0,
            4834000000.0,
            4836000000.0,
            4838000000.0,
            4840000000.0,
            4842000000.0,
            4844000000.0,
            4846000000.0,
            4848000000.0,
            4850000000.0,
            4852000000.0,
            4854000000.0,
            4856000000.0,
            4858000000.0,
            4860000000.0,
            4862000000.0,
            4864000000.0,
            4866000000.0,
            4868000000.0,
            4870000000.0,
            4872000000.0,
            4874000000.0,
            4876000000.0,
            4878000000.0,
            4880000000.0,
            4882000000.0,
            4884000000.0,
            4886000000.0,
            4888000000.0,
            4890000000.0,
            4892000000.0,
            4894000000.0,
            4896000000.0,
            4898000000.0,
            4900000000.0,
            4902000000.0,
            4904000000.0,
            4906000000.0,
            4908000000.0,
            4910000000.0,
            4912000000.0,
            4914000000.0,
            4916000000.0,
            4918000000.0,
            4920000000.0,
            4922000000.0,
            4924000000.0,
            4926000000.0,
            4928000000.0,
            4930000000.0,
            4932000000.0,
            4934000000.0,
            4936000000.0,
            4938000000.0,
            4940000000.0,
            4942000000.0,
            4944000000.0,
            4946000000.0,
            4948000000.0,
            4950000000.0,
            4952000000.0,
            4954000000.0,
            4956000000.0,
            4958000000.0,
            4960000000.0,
            4962000000.0,
            4964000000.0,
            4966000000.0,
            4968000000.0,
            4970000000.0,
            4972000000.0,
            4974000000.0,
            4976000000.0,
            4978000000.0,
            4980000000.0,
            4982000000.0,
            4984000000.0,
            4986000000.0,
            4988000000.0,
            4990000000.0,
            4992000000.0,
            4994000000.0,
            4996000000.0,
            4998000000.0,
            5000000000.0,
            5002000000.0,
            5004000000.0,
            5006000000.0,
            5008000000.0,
            5010000000.0,
            5012000000.0,
            5014000000.0,
            5016000000.0,
            5018000000.0,
            5020000000.0,
            5022000000.0,
            5024000000.0,
            5026000000.0,
            5028000000.0,
            5030000000.0
        ],
        "a_e": [
            5.04798234023048e-05,
            5.570368973748659e-05,
            5.895133438682621e-05,
            5.591808497701731e-05,
            5.438609273467559e-05,
            5.6842608031772726e-05,
            5.319013228058992e-05,
            5.529074555771645e-05,
            5.578203851232007e-05,
            5.585336140344251e-05,
            5.8524287180706696e-05,
            6.623868011840628e-05,
            7.293626541306176e-05,
            8.019228502322939e-05,
            8.563504437301044e-05,
            9.017175989209754e-05,
            9.452150667932057e-05,
            9.627265095862618e-05,
            0.00010732436202702171,
            0.00011072916780749192,
            0.00010450490640414803,
            0.0001099630788538352,
            0.00010096266478043263,
            9.969317867401525e-05,
            0.00010151442776882644,
            0.00010170467725080138,
            0.00010649827314783438,
            0.00011552935604822031,
            0.00010879248723063406,
            0.00010213812247937302,
            0.0001272707687995675,
            0.00011875848982016613,
            0.0001225433995971968,
            0.00013104127083822433,
            0.00012804765870575555,
            0.0001358342546796042,
            0.00014019886757673288,
            0.00013577037150328068,
            0.00013528856674396503,
            0.00014043364177030243,
            0.0001368129668634349,
            0.00012580201183296324,
            0.00011462057488338671,
            0.0001318858886115412,
            0.00010608012157637568,
            9.388180525921317e-05,
            7.575192548592477e-05,
            6.144819378702871e-05,
            3.8801156886575884e-05,
            2.8703802736885447e-05,
            4.193500042797411e-05,
            8.356641799674343e-05,
            0.00011442775898943141,
            0.0001323681915364579,
            0.00014236321610127599,
            0.00014514962547014303,
            0.0001530160306382899,
            0.00016073960011060432,
            0.00015224610912940105,
            0.00017571886232690164,
            0.000174950939711954,
            0.00018490317010115684,
            0.00020205700197125498,
            0.00020032010840205053,
            0.00021635611176784868,
            0.00021949795640550975,
            0.00023145409297854841,
            0.0002359687097896502,
            0.00023489982321040647,
            0.00022202998939906788,
            0.00021794063415693843,
            0.00019754709737967364,
            0.000183198387013255,
            0.00016519475990626797,
            0.0001504261389302769,
            0.00013878217760259723,
            0.00010988657144042269,
            0.00010043595644081291,
            9.118860054773751e-05,
            8.169792623775516e-05,
            5.180305485411715e-05,
            6.504060986901881e-05,
            5.346752232503595e-05,
            2.050646799317136e-05,
            1.5145793862959687e-05,
            2.2210823913525207e-05,
            1.7257297587530248e-05,
            3.555932049694597e-05,
            6.119225377042329e-05,
            9.054775297628172e-05,
            9.144455890566027e-05,
            9.686591488079504e-05,
            9.033152605127403e-05,
            0.00010319537811997007,
            0.00010187290380401147,
            0.00011368229532740384,
            0.0001161053266299548,
            0.00014628509510540677,
            0.00013158616122669364,
            0.0001524952979594053,
            0.00018180616978691647
        ],
        "a_g": [
            5.964266155704236e-05,
            4.9044837357657713e-05,
            6.687976478013425e-05,
            5.8936682933828825e-05,
            5.7462372771375765e-05,
            5.054773455194979e-05,
            5.024714327896762e-05,
            5.381620858962816e-05,
            6.186858653777306e-05,
            5.103053305231554e-05,
            6.411096865709907e-05,
            7.811619320984021e-05,
            7.428468832663871e-05,
            7.69310926029217e-05,
            8.383479758799224e-05,
            9.026100667184998e-05,
            9.688236108280242e-05,
            0.00010059665788053467,
            0.00010619617270370439,
            9.696162707087753e-05,
            0.00011244415465129791,
            9.84678456313415e-05,
            0.00010679821655212248,
            0.0001002895313254068,
            0.00011681462995943185,
            0.00010227343098029694,
            0.00011156830437613024,
            0.00010660143628175506,
            0.00011299473370443668,
            0.000100820631683454,
            0.00011827760178715298,
            0.00010721978885462017,
            0.0001339439706062386,
            0.00013502671639631215,
            0.0001302547294814411,
            0.0001376732422920976,
            0.00014175398437981998,
            0.0001363580118452671,
            0.00013467017638582105,
            0.0001369180871080876,
            0.00012119311947209746,
            0.0001223348229197464,
            0.00012191947556585685,
            0.00010799671115656427,
            8.71810417586317e-05,
            5.508392258886049e-05,
            4.0909640165268164e-05,
            3.182463950038812e-05,
            4.879638392768969e-05,
            9.163478595040957e-05,
            0.00011051002491339173,
            0.00011565165149787523,
            0.00013336685100239027,
            0.0001511391299050106,
            0.00015514155296971358,
            0.0001532668255369787,
            0.0001795685191956165,
            0.00017380410433611704,
            0.00016681619411891365,
            0.00019788739421889337,
            0.0001829520241358619,
            0.00019637787872705783,
            0.0002039463812351797,
            0.00020921685774835002,
            0.00021590519526678656,
            0.0002166587692317264,
            0.00020326982911477703,
            0.00021981938640302698,
            0.0002167249428842016,
            0.00021718469352300778,
            0.00019651102034001837,
            0.00018274592783586182,
            0.00017131233460401427,
            0.0001498901696518428,
            0.00013996095774210414,
            0.00012587372828655303,
            0.0001072342565065955,
            0.00010383639658791488,
            9.550472976717128e-05,
            7.610159939148954e-05,
            6.539391264868873e-05,
            5.306659609475689e-05,
            4.722620133996977e-05,
            3.409463483190014e-05,
            2.6393971886838375e-05,
            2.0589032650514422e-05,
            3.399737174525022e-05,
            4.3815847010584954e-05,
            6.203906200842028e-05,
            6.531470618578939e-05,
            8.703966336854487e-05,
            9.843886515207853e-05,
            9.789388983598989e-05,
            0.00010783987368638648,
            0.00011054241151881028,
            0.00012350814546757775,
            0.0001217091080768092,
            0.00012914195583166362,
            0.00013688382504143854,
            0.00016588918705536814,
            0.00016608035341681186
        ],
        "p_e": [
            -0.00011156708977137214,
            -0.00016286888814963225,
            -0.00021926136435354067,
            -0.00025381734984555334,
            -0.0002883402776172683,
            -0.00034507335267537745,
            -0.00035897196750561656,
            -0.00041415199101080274,
            -0.0004592678435600669,
            -0.0005004175207381856,
            -0.0005686916886926455,
            -0.0006952218313880502,
            -0.0008194190755600662,
            -0.0009640251955520241,
            -0.0010854642349445679,
            -0.0012170418914807623,
            -0.0013428515079798107,
            -0.0014381909196654866,
            -0.001681093319334412,
            -0.0018120037600188564,
            -0.00178526725421678,
            -0.0019641122597004053,
            -0.0018746540680351718,
            -0.0019252385563318514,
            -0.0020365988088071442,
            -0.002122362602900589,
            -0.0023081827919922394,
            -0.002577927960231645,
            -0.0025124051135367556,
            -0.0024531461556658294,
            -0.0031535233781643745,
            -0.003023505351315185,
            -0.0032222286895539887,
            -0.003552897276541894,
            -0.0035529275845546664,
            -0.0038821451896594865,
            -0.004113469796542573,
            -0.004090739175011055,
            -0.0041806857233172645,
            -0.0044516713951224095,
            -0.004436786640504444,
            -0.004185650375953116,
            -0.003917270652099784,
            -0.004595860308431296,
            -0.0037848413167415104,
            -0.0034301789703617184,
            -0.002835926230714269,
            -0.0023437638807001374,
            -0.0015001266664799648,
            -0.0011095080917649343,
            -0.0016160521663897611,
            -0.0032643525758159005,
            -0.004578407874301093,
            -0.005394630822415357,
            -0.00590923266055883,
            -0.006153104456065072,
            -0.00660334963332143,
            -0.007051537021718214,
            -0.006813382172544367,
            -0.008007075735450151,
            -0.00810263293177586,
            -0.008733082531746261,
            -0.009692587666608065,
            -0.009773582748605986,
            -0.01073134452345524,
            -0.01106867848722371,
            -0.011852221714551615,
            -0.012250424445461426,
            -0.012389173614348322,
            -0.011887679818009853,
            -0.01184156455276926,
            -0.010897954634568798,
            -0.010249672636840198,
            -0.00938805385819488,
            -0.008667208184284446,
            -0.008120251514258074,
            -0.0065259450054079345,
            -0.0060458473903249,
            -0.005556400753131283,
            -0.00503039183086369,
            -0.0032276062000863694,
            -0.004101309848128281,
            -0.0034171398224739358,
            -0.0013019037415218765,
            -0.0009821844979244073,
            -0.0014104864292648772,
            -0.0011179466152318825,
            -0.00230205912057402,
            -0.0040121273132689645,
            -0.0060084822446766425,
            -0.006105072204891393,
            -0.006546807093986771,
            -0.006171768595161478,
            -0.007122782042983753,
            -0.007120438698179542,
            -0.008013510403403139,
            -0.008309313259953996,
            -0.010552482018458775,
            -0.009597191527165313,
            -0.011228380306164857,
            -0.013523693780858536
        ],
        "p_g": [
            -0.0001309684298725682,
            -0.00014494245993165817,
            -0.00024845585417908734,
            -0.0002578965438849589,
            -0.0003013750642321493,
            -0.00030862444743590903,
            -0.00032887612502438584,
            -0.0004106609093377969,
            -0.0005010347419094222,
            -0.0004560108242566776,
            -0.0006303969872202721,
            -0.000821383184879763,
            -0.0008515647453344678,
            -0.0009213452788638959,
            -0.0010668561062714425,
            -0.0012110007147263014,
            -0.0013768869157442592,
            -0.0015023803743460511,
            -0.0016636765207286436,
            -0.001583267835644431,
            -0.001912246178795026,
            -0.001751809201215336,
            -0.0019788236922207293,
            -0.001939702881431201,
            -0.0023461454533244366,
            -0.0021363550879937524,
            -0.002424321940326906,
            -0.0023962164813819357,
            -0.002614405882203413,
            -0.0024101051855501595,
            -0.002916512121351985,
            -0.0027199929247654162,
            -0.0035271586415540042,
            -0.0036500490242580433,
            -0.003627843525452083,
            -0.003933989448768751,
            -0.004163317216558767,
            -0.004115644577141365,
            -0.004172441665168452,
            -0.004348765106295415,
            -0.0039493309489843365,
            -0.004098586198669177,
            -0.004184293252723813,
            -0.003794223226509524,
            -0.003156204860899145,
            -0.0020166882181970338,
            -0.0015266492980957028,
            -0.001185565018920873,
            -0.0018168677443752448,
            -0.003484672103505019,
            -0.0042702217275841685,
            -0.00455513968905757,
            -0.0053518907848851905,
            -0.006183851509515983,
            -0.0064672496795540445,
            -0.0065033947091821444,
            -0.007775458528528104,
            -0.007652603168450568,
            -0.007485299619771502,
            -0.009049264898656957,
            -0.008506821310222012,
            -0.009293306899182738,
            -0.009814027129020355,
            -0.01023543921443974,
            -0.010717462907496277,
            -0.01091894633837157,
            -0.010423391178670437,
            -0.011428925500493438,
            -0.011445178942549171,
            -0.01164468654573525,
            -0.010691700479270604,
            -0.010085912566415247,
            -0.009599265697052974,
            -0.008520515939212752,
            -0.00806965628662531,
            -0.0073911795682217625,
            -0.006372382157279933,
            -0.006256644280875846,
            -0.005840497220337088,
            -0.004691102986550067,
            -0.0040820565411457095,
            -0.0033585237725769356,
            -0.002993612111912181,
            -0.0021904349872162226,
            -0.0017048957428497833,
            -0.001313799071314061,
            -0.00218530361131899,
            -0.0028435460990188345,
            -0.004077329251645594,
            -0.00431145753220531,
            -0.005812615551678842,
            -0.006660363904160511,
            -0.006670526191512128,
            -0.007445112373339225,
            -0.007724814697316775,
            -0.008718491188973304,
            -0.008695898343982367,
            -0.00931863296371819,
            -0.00998498895671623,
            -0.01222519595366283,
            -0.012354898009526405
        ]
    }
}